circleci/__init__.py
smn-0.0.8.dist-info/LICENSE
smn-0.0.8.dist-info/METADATA
smn-0.0.8.dist-info/WHEEL
smn-0.0.8.dist-info/entry_points.txt
smn-0.0.8.dist-info/top_level.txt
smn-0.0.8.dist-info/RECORD
