Metadata-Version: 2.1
Name: smn
Version: 0.0.8
Summary: Share My Notebook
Home-page: https://github.com/xuxuehua/smn
Author: Xuehua Xu
Author-email: xuxuehua3@gmail.com
License: MIT License
Keywords: Notebook,Knowledge Base
Platform: UNKNOWN
Classifier: Development Status :: 5 - Production/Stable
Classifier: Intended Audience :: Developers
Classifier: Intended Audience :: System Administrators
Classifier: Programming Language :: Python :: 3
Classifier: License :: OSI Approved :: MIT License
Classifier: Operating System :: OS Independent
Classifier: Topic :: Software Development :: Build Tools
Classifier: Topic :: Software Development :: Libraries :: Python Modules
Classifier: Topic :: Internet
Classifier: Programming Language :: Python :: 3
Classifier: Programming Language :: Python :: 3.6
Classifier: Programming Language :: Python :: 3 :: Only
Requires-Python: >=3.6
Requires-Dist: fire (==0.3.1)
Requires-Dist: PyYAML (==5.3.1)
Requires-Dist: six (==1.14.0)
Requires-Dist: termcolor (==1.1.0)
